Icon
irf/Icon
irf/__init__.py
irf/irf_jupyter_utils.py
irf/irf_utils.py
irf/setup.py
irf/utils.py
irf/ensemble/Icon
irf/ensemble/__init__.py
irf/ensemble/wrf.py
irf/tests/Icon
irf/tests/__init__.py
irf/tests/test_irf_ensemble.py
irf/tests/test_irf_utils.py
irf/tests/test_irf_weighted.py
irf/tree/Icon
irf/tree/__init__.py
irf/tree/_criterion.cpython-37m-darwin.so
irf/tree/_splitter.cpython-37m-darwin.so
irf/tree/_tree.cpython-37m-darwin.so
irf/tree/_utils.cpython-37m-darwin.so
irf/tree/setup.py
irf/tree/tree.py
irf/tree/tests/Icon
irf/tree/tests/__init__.py
irf/tree/tests/test_export.py
irf/tree/tests/test_tree.py
irf-0.2.5.dist-info/COPYING
irf-0.2.5.dist-info/Icon
irf-0.2.5.dist-info/METADATA
irf-0.2.5.dist-info/WHEEL
irf-0.2.5.dist-info/top_level.txt
irf-0.2.5.dist-info/RECORD
