Metadata-Version: 2.1
Name: irf
Version: 0.2.5
Summary: irf
Home-page: https://github.com/Yu-Group/irf
Maintainer: Many
Maintainer-email: many@berkeley.edu
License: new BSD
Platform: UNKNOWN
Classifier: Intended Audience :: Science/Research
Classifier: Intended Audience :: Developers
Classifier: License :: OSI Approved
Classifier: Programming Language :: C
Classifier: Programming Language :: Python
Classifier: Topic :: Software Development
Classifier: Topic :: Scientific/Engineering
Classifier: Operating System :: Microsoft :: Windows
Classifier: Operating System :: POSIX
Classifier: Operating System :: Unix
Classifier: Operating System :: MacOS
License-File: COPYING
Requires-Dist: numpy
Requires-Dist: scipy
Requires-Dist: scikit-learn (>=0.22)
Requires-Dist: cython
Requires-Dist: pyfpgrowth
Requires-Dist: pyspark
Requires-Dist: pyyaml
Requires-Dist: pydotplus
